pycmakebuild/__init__.py
pycmakebuild/__main__.py
pycmakebuild/api.py
pycmakebuild-0.2.27.dist-info/METADATA
pycmakebuild-0.2.27.dist-info/WHEEL
pycmakebuild-0.2.27.dist-info/entry_points.txt
pycmakebuild-0.2.27.dist-info/top_level.txt
pycmakebuild-0.2.27.dist-info/RECORD
