Metadata-Version: 2.4
Name: pycmakebuild
Version: 0.2.27
Summary: Python CMake批量构建工具，支持变量替换、多项目管理、跨平台自动化编译，通过build.json配置实现CMake项目的统一构建流程
Author-email: PatchLion <747497016@qq.com>
License: MIT
Project-URL: Homepage, https://gitee.com/PatchLion/pycmakebuild
Requires-Python: >=3.6
Requires-Dist: cmake<4.0,>=3.0
